eyelet/__init__.py
eyelet/__main__.py
eyelet/application/__init__.py
eyelet/application/discovery.py
eyelet/application/services.py
eyelet/cli/__init__.py
eyelet/cli/completion.py
eyelet/cli/configure.py
eyelet/cli/discover.py
eyelet/cli/doctor.py
eyelet/cli/execute.py
eyelet/cli/execute_old.py
eyelet/cli/execute_v2.py
eyelet/cli/logs.py
eyelet/cli/main.py
eyelet/cli/query.py
eyelet/cli/recall.py
eyelet/cli/template.py
eyelet/cli/utils.py
eyelet/cli/validate.py
eyelet/domain/__init__.py
eyelet/domain/config.py
eyelet/domain/exceptions.py
eyelet/domain/hooks.py
eyelet/domain/models.py
eyelet/infrastructure/__init__.py
eyelet/infrastructure/database.py
eyelet/infrastructure/repositories.py
eyelet/presentation/__init__.py
eyelet/presentation/tui.py
eyelet/recall/__init__.py
eyelet/recall/loader.py
eyelet/recall/migrations.py
eyelet/recall/models.py
eyelet/recall/parser.py
eyelet/recall/search.py
eyelet/schemas/claude-settings.schema.json
eyelet/services/config_service.py
eyelet/services/git_metadata.py
eyelet/services/hook_logger.py
eyelet/services/query_service.py
eyelet/services/sqlite_connection.py
eyelet/services/sqlite_logger.py
eyelet/services/sqlite_migrations.py
eyelet/services/sqlite_monitor.py
eyelet/templates/__init__.py
eyelet/templates/generators.py
eyelet/tui/__init__.py
eyelet/tui/app.py
eyelet/tui/app.tcss
eyelet/tui/themes.py
eyelet/tui/screens/__init__.py
eyelet/tui/screens/configure.py
eyelet/tui/screens/configure_hooks.py
eyelet/tui/screens/help.py
eyelet/tui/screens/logs.py
eyelet/tui/screens/recall.py
eyelet/tui/screens/settings.py
eyelet/tui/screens/templates.py
eyelet-0.3.5.dist-info/licenses/LICENSE
eyelet-0.3.5.dist-info/METADATA
eyelet-0.3.5.dist-info/WHEEL
eyelet-0.3.5.dist-info/entry_points.txt
eyelet-0.3.5.dist-info/top_level.txt
eyelet-0.3.5.dist-info/RECORD
